{
  "kind": "rss",
  "title": "Search Central Live is coming back to South America",
  "link": "https://developers.google.com/search/blog/2026/01/search-central-live-brasil-argentina",
  "guid": "2026-01-26-Search-Central-Live-is-coming-back-to-South-America",
  "pubDate": "Mon, 26 Jan 2026 00:00:00 +0000",
  "summary": "We're excited to announce that Search Central Live is returning to São Paulo and to Buenos Aires in 2026. Following many years of successful events in the region, we're continuing our mission to help local businesses enhance their site's performance in Google Search.",
  "sourceFeed": "Google Search Central",
  "sourceUrl": "https://feeds.feedburner.com/blogspot/amDG",
  "ingestedAt": "2026-04-08T14:45:58.560Z",
  "suggestedFilename": "2026-01-26-search-central-live-is-coming-back-to-south-amer.md"
}
